{"command":[{"command":"..\\adfind.exe"},{"argument":"-regex?"}],"modifiers":{"QuoteInsertion":{"ExcludedTypes":["command"],"Probability":"0.5"},"RandomCase":{"ExcludedTypes":["url","value"],"Probability":"0.5"},"OptionCharSubstitution":{"ExcludedTypes":["command","path","value","url"],"Probability":"0.5","OutputOptionChars":["-","/","‐","‒","–","―","⁄","−","∕","－"]},"Sed":{"ExcludedTypes":["command","path","url","value"],"Probability":"0.5","SedStatements":"s/a/ａ|α|Ā|ā|Ă|ă|Ą|ą|Ａ/i\ns/b/ｂ|Ｂ|ℬ/i\ns/c/ｃ|Ć|ć|Ĉ|ĉ|Ċ|ċ|Č|č|Ｃ|ℂ/i\ns/d/ｄ|Ď|ď|Đ|đ|ı|Ｄ/i\ns/e/ｅ|℮|ℯ|Ē|ē|Ĕ|ĕ|Ė|ė|Ę|ę|Ě|ě|Ｅ|ℇ/i\ns/f/ｆ|Ｆ|ℱ/i\ns/g/ｇ|ℊ|Ｇ|Ǥ|Ğ|Ĝ|ĝ|Ğ|ğ|Ġ|ġ|Ģ|ģ/i\ns/h/ｈ|Ĥ|ĥ|Ħ|ħ|Ｈ|ℍ|ℋ/i\ns/i/ｉ|Ĩ|ĩ|Ī|ī|Ĭ|ĭ|Į|į|İ|Ｉ|ℐ|ℑ/i\ns/j/ｊ|Ĵ|ĵ|Ｊ/i\ns/k/ｋ|Ķ|ķ|ĸ|Ｋ/i\ns/l/ｌ|ℓ|Ĺ|ĺ|Ļ|ļ|Ľ|ľ|Ŀ|ŀ|Ł|ł|Ｌ|ℒ|Ĺ/i\ns/m/ｍ|Ｍ|ℳ/i\ns/n/ｎ|ń|Ń|ń|Ņ|ņ|Ň|ň|ŉ|Ｎ|ℕ|Ń/i\ns/o/ｏ|ℴ|Ｏ|Ō|ō|Ŏ|ŏ|Ő|ő/i\ns/p/ｐ|Ｐ|ℙ/i\ns/q/ｑ|Ｑ|ℚ/i\ns/r/ｒ|Ŕ|ŕ|Ŗ|ŗ|Ř|ř|Ｒ|ℝ/i\ns/s/ｓ|Ś|ś|Ŝ|ŝ|Ş|ş|Š|š|Ｓ/i\ns/t/ｔ|Ţ|ţ|Ť|ť|Ŧ|ŧ|Ｔ/i\ns/u/ｕ|Ũ|ũ|Ū|ū|Ŭ|ŭ|Ů|ů|Ű|ű|Ų|ų|Ｕ/i\ns/v/ｖ|Ｖ/i\ns/w/ｗ|Ｗ|Ŵ|ŵ/i\ns/x/ｘ|Ｘ/i\ns/y/ｙ|Ŷ|ŷ|Ÿ|Ｙ/i\ns/z/ｚ|Ｚ|ℤ|Ź|ź|Ż|ż|Ž|ž/i\ns/\\//／/i\ns/:/：/i\ns/\"/＂/i\ns/0/０/i"}}}
