{"command":[{"command":"wscript"},{"value":"lalala"}],"modifiers":{"Regex":{"ExcludedTypes":["command","path","url","value"],"Probability":"1","RegexMatch":"/?/","RegexReplace":"//","CaseSensitive":false},"Sed":{"ExcludedTypes":["command","path","url","value"],"Probability":"0.5","SedStatements":"s/\\/\\//\\/|\\/\\//"},"FilePathTransformer":{"ExcludedTypes":["command","argument","value","url"],"Probability":"0.5","PathTraversal":true,"SubstituteSlashes":true,"ExtraSlashes":true},"QuoteInsertion":{"ExcludedTypes":["command"],"Probability":"0.5"},"RandomCase":{"ExcludedTypes":[],"Probability":"0.5"}}}
